{
  "_format": "hh-sol-cache-2",
  "files": {
    "/Users/Chitrang.Mevawala/Documents/optilistic/kickstarter-clone/contracts/KickStarter.sol": {
      "lastModificationDate": 1632403709369,
      "contentHash": "9a0c5198dfef3c47417cd827e626a790",
      "sourceName": "contracts/KickStarter.sol",
      "solcConfig": {
        "version": "0.8.7",
        "settings": {
          "optimizer": {
            "enabled": false,
            "runs": 200
          },
          "outputSelection": {
            "*": {
              "*": [
                "abi",
                "evm.bytecode",
                "evm.deployedBytecode",
                "evm.methodIdentifiers"
              ],
              "": [
                "ast"
              ]
            }
          }
        }
      },
      "imports": [],
      "versionPragmas": [
        "^0.8.7"
      ],
      "artifacts": [
        "KickStarter"
      ]
    },
    "/Users/Chitrang.Mevawala/Documents/optilistic/kickstarter-clone/contracts/Token.sol": {
      "lastModificationDate": 1632244912622,
      "contentHash": "489abe1b96276d118d560eefbc89d931",
      "sourceName": "contracts/Token.sol",
      "solcConfig": {
        "version": "0.8.7",
        "settings": {
          "optimizer": {
            "enabled": false,
            "runs": 200
          },
          "outputSelection": {
            "*": {
              "*": [
                "abi",
                "evm.bytecode",
                "evm.deployedBytecode",
                "evm.methodIdentifiers"
              ],
              "": [
                "ast"
              ]
            }
          }
        }
      },
      "imports": [],
      "versionPragmas": [
        "^0.8.7"
      ],
      "artifacts": [
        "Token"
      ]
    },
    "/Users/Chitrang.Mevawala/Documents/optilistic/kickstarter-clone/contracts/TimeStamp.sol": {
      "lastModificationDate": 1632311179601,
      "contentHash": "f7f9acbcd617ac6ce461e78ff95883e7",
      "sourceName": "contracts/TimeStamp.sol",
      "solcConfig": {
        "version": "0.8.7",
        "settings": {
          "optimizer": {
            "enabled": false,
            "runs": 200
          },
          "outputSelection": {
            "*": {
              "*": [
                "abi",
                "evm.bytecode",
                "evm.deployedBytecode",
                "evm.methodIdentifiers"
              ],
              "": [
                "ast"
              ]
            }
          }
        }
      },
      "imports": [],
      "versionPragmas": [
        "^0.8.7"
      ],
      "artifacts": [
        "Timestamp"
      ]
    },
    "/Users/Chitrang.Mevawala/Documents/optilistic/kickstarter-clone/contracts/KickStarterFactory.sol": {
      "lastModificationDate": 1632418224407,
      "contentHash": "c3b187cc956365aac76a4306c897c190",
      "sourceName": "contracts/KickStarterFactory.sol",
      "solcConfig": {
        "version": "0.8.7",
        "settings": {
          "optimizer": {
            "enabled": false,
            "runs": 200
          },
          "outputSelection": {
            "*": {
              "*": [
                "abi",
                "evm.bytecode",
                "evm.deployedBytecode",
                "evm.methodIdentifiers"
              ],
              "": [
                "ast"
              ]
            }
          }
        }
      },
      "imports": [],
      "versionPragmas": [
        "^0.8.7"
      ],
      "artifacts": [
        "KickStarterFactory",
        "Project"
      ]
    }
  }
}
